odoo/addons/ssi_timesheet/README.rst
odoo/addons/ssi_timesheet/__init__.py
odoo/addons/ssi_timesheet/__manifest__.py
odoo/addons/ssi_timesheet/menu.xml
odoo/addons/ssi_timesheet/data/approval_template_data.xml
odoo/addons/ssi_timesheet/data/ir_sequence_data.xml
odoo/addons/ssi_timesheet/data/policy_template_data.xml
odoo/addons/ssi_timesheet/data/sequence_template_data.xml
odoo/addons/ssi_timesheet/models/__init__.py
odoo/addons/ssi_timesheet/models/hr_employee.py
odoo/addons/ssi_timesheet/models/hr_timesheet.py
odoo/addons/ssi_timesheet/models/hr_timesheet_computation.py
odoo/addons/ssi_timesheet/models/hr_timesheet_computation_item.py
odoo/addons/ssi_timesheet/models/hr_timesheet_daily_summary.py
odoo/addons/ssi_timesheet/reports/__init__.py
odoo/addons/ssi_timesheet/reports/hr_timesheet_computation_analysis.py
odoo/addons/ssi_timesheet/reports/hr_timesheet_computation_analysis.xml
odoo/addons/ssi_timesheet/security/ir.model.access.csv
odoo/addons/ssi_timesheet/security/ir_module_category_data.xml
odoo/addons/ssi_timesheet/security/ir_rule_data.xml
odoo/addons/ssi_timesheet/security/res_group_data.xml
odoo/addons/ssi_timesheet/static/description/icon.png
odoo/addons/ssi_timesheet/static/description/icon_timesheet.png
odoo/addons/ssi_timesheet/views/hr_employee_views.xml
odoo/addons/ssi_timesheet/views/hr_timesheet_computation_item_views.xml
odoo/addons/ssi_timesheet/views/hr_timesheet_views.xml
odoo/addons/ssi_timesheet/wizards/__init__.py
odoo/addons/ssi_timesheet/wizards/generate_timesheet.py
odoo/addons/ssi_timesheet/wizards/generate_timesheet.xml
odoo14_addon_ssi_timesheet-14.0.2.1.0.dist-info/METADATA
odoo14_addon_ssi_timesheet-14.0.2.1.0.dist-info/WHEEL
odoo14_addon_ssi_timesheet-14.0.2.1.0.dist-info/top_level.txt
odoo14_addon_ssi_timesheet-14.0.2.1.0.dist-info/RECORD
